{
    "filer": {
        "isActive": true,
        "cpfId": 17580,
        "accountType": {
            "code": "D",
            "description": "Depository Candidate",
            "display": "D   Depository Candidate",
            "isCandidate": true,
            "isDepository": true,
            "isPac": false,
            "isBq": false,
            "isLpc": false,
            "isBank": false,
            "isPeoplesCommittee": false,
            "isSegregatedFund": false,
            "isLegislative": false,
            "isNonPartisan": false,
            "isLocalFiler": false,
            "isLegacyPac": false,
            "isIePac": false,
            "isStateParty": false
        },
        "candidateFirstName": "Frantz",
        "candidateLastName": "Pierre",
        "fullNameReverse": "Pierre, Frantz",
        "fullName": "Frantz Pierre",
        "committeeName": "Pierre Committee",
        "committeePurpose": "",
        "organizationDate": "11/10/2020",
        "closedDate": "",
        "candidate": {
            "salutation": "Mr.",
            "defaultSalutation": "Mr.",
            "firstName": "Frantz",
            "middleName": "",
            "lastName": "Pierre",
            "suffix": "",
            "streetAddress": "22 Water Street, Unit 808",
            "careOf": "",
            "city": "Cambridge",
            "state": "MA",
            "zipCode": "02141",
            "zip": "02141",
            "fullAddress": "22 Water Street, Unit 808 Cambridge, MA  02141",
            "phoneNumber": "",
            "emailAddress": "",
            "fullName": "Frantz Pierre",
            "fullNameReverse": "Pierre, Frantz"
        },
        "treasurer": {
            "salutation": "Ms.",
            "defaultSalutation": "",
            "firstName": "Sharay",
            "middleName": "",
            "lastName": "Howard",
            "suffix": "",
            "streetAddress": "22 Water Street, Unit 808",
            "careOf": "",
            "city": "Cambridge",
            "state": "MA",
            "zipCode": "02141",
            "zip": "02141",
            "fullAddress": "22 Water Street, Unit 808 Cambridge, MA  02141",
            "phoneNumber": "",
            "emailAddress": "",
            "fullName": "Sharay Howard",
            "fullNameReverse": "Howard, Sharay"
        },
        "chairman": {
            "salutation": "Ms.",
            "defaultSalutation": "",
            "firstName": "Nirva",
            "middleName": "",
            "lastName": "Guirand",
            "suffix": "",
            "streetAddress": "2 Leighton Street, Unit 231",
            "careOf": "",
            "city": "Cambridge",
            "state": "MA",
            "zipCode": "02141",
            "zip": "02141",
            "fullAddress": "2 Leighton Street, Unit 231 Cambridge, MA  02141",
            "phoneNumber": "",
            "emailAddress": "",
            "fullName": "Nirva Guirand",
            "fullNameReverse": "Guirand, Nirva"
        },
        "isCandidateOnly": false,
        "officeSought": {
            "districtCode": 5049,
            "officeDescription": "City Councilor",
            "districtDescription": "Cambridge",
            "officeDistrict": "City Councilor, Cambridge",
            "display": "5049   City Councilor, Cambridge"
        },
        "officeHeld": {
            "districtCode": 0,
            "officeDescription": "N/A",
            "districtDescription": "No office",
            "officeDistrict": "N/A, No office",
            "display": "0      N/A, No office"
        },
        "officeSoughtDescription": "City Councilor, Cambridge",
        "partyAffiliation": "Unenrolled",
        "bankId": 60096,
        "bankName": "Leader Bank",
        "tags": [
            {
                "id": 12812,
                "cpfId": 17580,
                "tagTypeId": 1,
                "tagTypeDescription": "On Ballot",
                "year": 2023,
                "officeType": "City Councilor",
                "districtCode": 5049,
                "isSpecialElection": false,
                "districtDescription": "Cambridge",
                "filerName": null,
                "bqQuestionId": 0,
                "bqQuestionDescription": null,
                "bqPosition": null,
                "description": "2023 On Ballot  - "
            },
            {
                "id": 11260,
                "cpfId": 17580,
                "tagTypeId": 1,
                "tagTypeDescription": "On Ballot",
                "year": 2021,
                "officeType": "City Councilor",
                "districtCode": 5049,
                "isSpecialElection": false,
                "districtDescription": "Cambridge",
                "filerName": null,
                "bqQuestionId": 0,
                "bqQuestionDescription": null,
                "bqPosition": null,
                "description": "2021 On Ballot  - "
            }
        ],
        "organizationStatementBlobUrl": "https://ocpf2.blob.core.windows.net/pdf/filers/17580/17580-cpf101-1-111020.pdf",
        "organizationStatementFileName": "17580-cpf101-1-111020.pdf",
        "filerPhotoUrl": "",
        "isCandidate": true,
        "isBq": false
    },
    "logReports": [
        {
            "cpfId": 17580,
            "reportId": 969232,
            "reportTypeId": 70,
            "reportTypeDescription": "Bank Report",
            "reportingPeriod": "3/1 - 3/31/2025",
            "dateFiled": "Fri, 4/4/2025 11:08 AM",
            "dateFiledHeader": "Fri, 4/4/2025",
            "fullNameReverse": "Pierre, Frantz",
            "officeSought": "City Councilor Cambridge",
            "reportLink": "https://www.ocpf.us/Reports/DisplayReport?menuHidden=true&id=969232",
            "amendmentDisplay": "",
            "expenditureTotal": "$0.00",
            "receiptTotal": "$0.00",
            "miscellaneousCandidateList": "",
            "bqDescription": "",
            "color": "PaleGoldenrod"
        },
        {
            "cpfId": 17580,
            "reportId": 964578,
            "reportTypeId": 70,
            "reportTypeDescription": "Bank Report",
            "reportingPeriod": "2/1 - 2/28-9/2025",
            "dateFiled": "Mon, 3/3/2025 12:47 PM",
            "dateFiledHeader": "Mon, 3/3/2025",
            "fullNameReverse": "Pierre, Frantz",
            "officeSought": "City Councilor Cambridge",
            "reportLink": "https://www.ocpf.us/Reports/DisplayReport?menuHidden=true&id=964578",
            "amendmentDisplay": "",
            "expenditureTotal": "$0.00",
            "receiptTotal": "$0.00",
            "miscellaneousCandidateList": "",
            "bqDescription": "",
            "color": "PaleGoldenrod"
        },
        {
            "cpfId": 17580,
            "reportId": 962719,
            "reportTypeId": 70,
            "reportTypeDescription": "Bank Report",
            "reportingPeriod": "1/1 - 1/31/2025",
            "dateFiled": "Tue, 2/4/2025 8:53 AM",
            "dateFiledHeader": "Tue, 2/4/2025",
            "fullNameReverse": "Pierre, Frantz",
            "officeSought": "City Councilor Cambridge",
            "reportLink": "https://www.ocpf.us/Reports/DisplayReport?menuHidden=true&id=962719",
            "amendmentDisplay": "",
            "expenditureTotal": "$0.00",
            "receiptTotal": "$0.00",
            "miscellaneousCandidateList": "",
            "bqDescription": "",
            "color": "PaleGoldenrod"
        },
        {
            "cpfId": 17580,
            "reportId": 958542,
            "reportTypeId": 11,
            "reportTypeDescription": "Year-End Report",
            "reportingPeriod": "1/1/24 - 12/31/24",
            "dateFiled": "Tue, 1/7/2025 5:40 PM",
            "dateFiledHeader": "Tue, 1/7/2025",
            "fullNameReverse": "Pierre, Frantz",
            "officeSought": "City Councilor Cambridge",
            "reportLink": "https://www.ocpf.us/Reports/DisplayReport?menuHidden=true&id=958542",
            "amendmentDisplay": "",
            "expenditureTotal": "$584.44",
            "receiptTotal": "$489.52",
            "miscellaneousCandidateList": "",
            "bqDescription": "",
            "color": "LightGreen"
        },
        {
            "cpfId": 17580,
            "reportId": 958541,
            "reportTypeId": 60,
            "reportTypeDescription": "Deposit Report",
            "reportingPeriod": "9/23/24",
            "dateFiled": "Tue, 1/7/2025 5:38 PM",
            "dateFiledHeader": "Tue, 1/7/2025",
            "fullNameReverse": "Pierre, Frantz",
            "officeSought": "City Councilor Cambridge",
            "reportLink": "https://www.ocpf.us/Reports/DisplayReport?menuHidden=true&id=958541",
            "amendmentDisplay": "",
            "expenditureTotal": "$0.00",
            "receiptTotal": "$461.00",
            "miscellaneousCandidateList": "",
            "bqDescription": "",
            "color": "SkyBlue"
        }
    ],
    "ytdReport": {
        "cpfId": 17580,
        "filerName": "Pierre, Frantz",
        "officeSought": "City Councilor, Cambridge",
        "districtCodeSought": 5049,
        "districtCodeHeld": 0,
        "receiptsYtdNumeric": 0.0,
        "expendituresYtdNumeric": 0.0,
        "currentCashOnHandNumeric": 306.04,
        "receiptsYtd": "$0.00",
        "expendituresYtd": "$0.00",
        "currentCashOnHand": "$306.04",
        "startBalanceNumeric": 306.04,
        "startBalance": "$306.04",
        "bankReportId": 969232,
        "bankReportEndDate": "3/31/2025",
        "reportYearFirstDayDate": "1/1/2025",
        "partyAffiliation": "",
        "isWinner": false
    },
    "isMissingTreasurerTraining": true,
    "treasurerTrainingStatus": "Missing Training"
}